{"time_proj": [981], "time_embedding": [1.0, 0], "time_embedding.linear_1": [1.0], "time_embedding.act": [110.1085433959961], "time_embedding.linear_2": [8.328484535217285], "conv_in": [8.862883567810059], "down_blocks.0.resnets.0": [13.203079223632812, 5.55919885635376], "down_blocks.0.resnets.0.norm1": [13.203079223632812], "down_blocks.0.resnets.0.conv1": [7.048758029937744], "down_blocks.0.resnets.0.time_emb_proj": [5.537867546081543], "down_blocks.0.resnets.0.norm2": [38.32783508300781], "down_blocks.0.resnets.0.dropout": [16.907806396484375], "down_blocks.0.resnets.0.conv2": [16.907806396484375], "down_blocks.0.attentions.0": [46.4801025390625], "down_blocks.0.attentions.0.norm": [46.4801025390625], "down_blocks.0.attentions.0.proj_in": [8.313505172729492], "down_blocks.0.attentions.0.transformer_blocks.0": [2.694136619567871], "down_blocks.0.attentions.0.transformer_blocks.0.norm1": [2.694136619567871], "down_blocks.0.attentions.0.transformer_blocks.0.attn1": [3.1075241565704346], "down_blocks.0.attentions.0.transformer_blocks.0.attn1.to_q": [3.1075241565704346], "down_blocks.0.attentions.0.transformer_blocks.0.attn1.to_k": [3.1075241565704346], "down_blocks.0.attentions.0.transformer_blocks.0.attn1.to_v": [3.1075241565704346], "down_blocks.0.attentions.0.transformer_blocks.0.attn1.to_out.0": [2.728498697280884], "down_blocks.0.attentions.0.transformer_blocks.0.attn1.to_out.1": [1.904309630393982], "down_blocks.0.attentions.0.transformer_blocks.0.norm2": [2.740309476852417], "down_blocks.0.attentions.0.transformer_blocks.0.attn2": [2.6754682064056396], "down_blocks.0.attentions.0.transformer_blocks.0.attn2.to_q": [2.6754682064056396], "down_blocks.0.attentions.0.transformer_blocks.0.attn2.to_k": [13.78433895111084], "down_blocks.0.attentions.0.transformer_blocks.0.attn2.to_v": [13.78433895111084], "down_blocks.0.attentions.0.transformer_blocks.0.attn2.to_out.0": [5.932799816131592], "down_blocks.0.attentions.0.transformer_blocks.0.attn2.to_out.1": [0.8002359867095947], "down_blocks.0.attentions.0.transformer_blocks.0.norm3": [3.2280924320220947], "down_blocks.0.attentions.0.transformer_blocks.0.ff": [2.5619046688079834], "down_blocks.0.attentions.0.transformer_blocks.0.ff.net.0": [2.5619046688079834], "down_blocks.0.attentions.0.transformer_blocks.0.ff.net.0.proj": [2.5619046688079834], "down_blocks.0.attentions.0.transformer_blocks.0.ff.net.1": [25.33509063720703], "down_blocks.0.attentions.0.transformer_blocks.0.ff.net.2": [25.33509063720703], "down_blocks.0.attentions.0.proj_out": [12.4675931930542], "down_blocks.0.resnets.1": [11.616290092468262, 5.55919885635376], "down_blocks.0.resnets.1.norm1": [11.616290092468262], "down_blocks.0.resnets.1.conv1": [3.661869525909424], "down_blocks.0.resnets.1.time_emb_proj": [5.537867546081543], "down_blocks.0.resnets.1.norm2": [6.238395690917969], "down_blocks.0.resnets.1.dropout": [4.996974945068359], "down_blocks.0.resnets.1.conv2": [4.996974945068359], "down_blocks.0.attentions.1": [11.723235130310059], "down_blocks.0.attentions.1.norm": [11.723235130310059], "down_blocks.0.attentions.1.proj_in": [4.139828681945801], "down_blocks.0.attentions.1.transformer_blocks.0": [4.885083198547363], "down_blocks.0.attentions.1.transformer_blocks.0.norm1": [4.885083198547363], "down_blocks.0.attentions.1.transformer_blocks.0.attn1": [3.895906686782837], "down_blocks.0.attentions.1.transformer_blocks.0.attn1.to_q": [3.895906686782837], "down_blocks.0.attentions.1.transformer_blocks.0.attn1.to_k": [3.895906686782837], "down_blocks.0.attentions.1.transformer_blocks.0.attn1.to_v": [3.895906686782837], "down_blocks.0.attentions.1.transformer_blocks.0.attn1.to_out.0": [3.3408584594726562], "down_blocks.0.attentions.1.transformer_blocks.0.attn1.to_out.1": [2.9137766361236572], "down_blocks.0.attentions.1.transformer_blocks.0.norm2": [6.65788459777832], "down_blocks.0.attentions.1.transformer_blocks.0.attn2": [4.0134196281433105], "down_blocks.0.attentions.1.transformer_blocks.0.attn2.to_q": [4.0134196281433105], "down_blocks.0.attentions.1.transformer_blocks.0.attn2.to_k": [13.78433895111084], "down_blocks.0.attentions.1.transformer_blocks.0.attn2.to_v": [13.78433895111084], "down_blocks.0.attentions.1.transformer_blocks.0.attn2.to_out.0": [5.276005744934082], "down_blocks.0.attentions.1.transformer_blocks.0.attn2.to_out.1": [1.9390628337860107], "down_blocks.0.attentions.1.transformer_blocks.0.norm3": [6.886092185974121], "down_blocks.0.attentions.1.transformer_blocks.0.ff": [2.375199556350708], "down_blocks.0.attentions.1.transformer_blocks.0.ff.net.0": [2.375199556350708], "down_blocks.0.attentions.1.transformer_blocks.0.ff.net.0.proj": [2.375199556350708], "down_blocks.0.attentions.1.transformer_blocks.0.ff.net.1": [7.805047988891602], "down_blocks.0.attentions.1.transformer_blocks.0.ff.net.2": [7.805047988891602], "down_blocks.0.attentions.1.proj_out": [7.522284984588623], "down_blocks.0.downsamplers.0": [10.70036792755127], "down_blocks.0.downsamplers.0.conv": [10.70036792755127], "down_blocks.1.resnets.0": [22.361608505249023, 5.55919885635376], "down_blocks.1.resnets.0.norm1": [22.361608505249023], "down_blocks.1.resnets.0.conv1": [3.5864362716674805], "down_blocks.1.resnets.0.time_emb_proj": [5.537867546081543], "down_blocks.1.resnets.0.norm2": [32.860862731933594], "down_blocks.1.resnets.0.dropout": [8.01637077331543], "down_blocks.1.resnets.0.conv2": [8.01637077331543], "down_blocks.1.resnets.0.conv_shortcut": [22.361608505249023], "down_blocks.1.attentions.0": [15.004569053649902], "down_blocks.1.attentions.0.norm": [15.004569053649902], "down_blocks.1.attentions.0.proj_in": [2.9643337726593018], "down_blocks.1.attentions.0.transformer_blocks.0": [8.594768524169922], "down_blocks.1.attentions.0.transformer_blocks.0.norm1": [8.594768524169922], "down_blocks.1.attentions.0.transformer_blocks.0.attn1": [2.728337526321411], "down_blocks.1.attentions.0.transformer_blocks.0.attn1.to_q": [2.728337526321411], "down_blocks.1.attentions.0.transformer_blocks.0.attn1.to_k": [2.728337526321411], "down_blocks.1.attentions.0.transformer_blocks.0.attn1.to_v": [2.728337526321411], "down_blocks.1.attentions.0.transformer_blocks.0.attn1.to_out.0": [2.9675755500793457], "down_blocks.1.attentions.0.transformer_blocks.0.attn1.to_out.1": [4.671931743621826], "down_blocks.1.attentions.0.transformer_blocks.0.norm2": [8.060443878173828], "down_blocks.1.attentions.0.transformer_blocks.0.attn2": [3.42582368850708], "down_blocks.1.attentions.0.transformer_blocks.0.attn2.to_q": [3.42582368850708], "down_blocks.1.attentions.0.transformer_blocks.0.attn2.to_k": [13.78433895111084], "down_blocks.1.attentions.0.transformer_blocks.0.attn2.to_v": [13.78433895111084], "down_blocks.1.attentions.0.transformer_blocks.0.attn2.to_out.0": [7.8114914894104], "down_blocks.1.attentions.0.transformer_blocks.0.attn2.to_out.1": [2.020522117614746], "down_blocks.1.attentions.0.transformer_blocks.0.norm3": [8.777605056762695], "down_blocks.1.attentions.0.transformer_blocks.0.ff": [4.014532089233398], "down_blocks.1.attentions.0.transformer_blocks.0.ff.net.0": [4.014532089233398], "down_blocks.1.attentions.0.transformer_blocks.0.ff.net.0.proj": [4.014532089233398], "down_blocks.1.attentions.0.transformer_blocks.0.ff.net.1": [12.193448066711426], "down_blocks.1.attentions.0.transformer_blocks.0.ff.net.2": [12.193448066711426], "down_blocks.1.attentions.0.proj_out": [8.861477851867676], "down_blocks.1.resnets.1": [16.81192970275879, 5.55919885635376], "down_blocks.1.resnets.1.norm1": [16.81192970275879], "down_blocks.1.resnets.1.conv1": [5.286574840545654], "down_blocks.1.resnets.1.time_emb_proj": [5.537867546081543], "down_blocks.1.resnets.1.norm2": [8.929649353027344], "down_blocks.1.resnets.1.dropout": [7.589015483856201], "down_blocks.1.resnets.1.conv2": [7.589015483856201], "down_blocks.1.attentions.1": [13.598468780517578], "down_blocks.1.attentions.1.norm": [13.598468780517578], "down_blocks.1.attentions.1.proj_in": [3.327806234359741], "down_blocks.1.attentions.1.transformer_blocks.0": [17.58079719543457], "down_blocks.1.attentions.1.transformer_blocks.0.norm1": [17.58079719543457], "down_blocks.1.attentions.1.transformer_blocks.0.attn1": [3.885233163833618], "down_blocks.1.attentions.1.transformer_blocks.0.attn1.to_q": [3.885233163833618], "down_blocks.1.attentions.1.transformer_blocks.0.attn1.to_k": [3.885233163833618], "down_blocks.1.attentions.1.transformer_blocks.0.attn1.to_v": [3.885233163833618], "down_blocks.1.attentions.1.transformer_blocks.0.attn1.to_out.0": [2.8787684440612793], "down_blocks.1.attentions.1.transformer_blocks.0.attn1.to_out.1": [10.196306228637695], "down_blocks.1.attentions.1.transformer_blocks.0.norm2": [18.51344871520996], "down_blocks.1.attentions.1.transformer_blocks.0.attn2": [5.395395278930664], "down_blocks.1.attentions.1.transformer_blocks.0.attn2.to_q": [5.395395278930664], "down_blocks.1.attentions.1.transformer_blocks.0.attn2.to_k": [13.78433895111084], "down_blocks.1.attentions.1.transformer_blocks.0.attn2.to_v": [13.78433895111084], "down_blocks.1.attentions.1.transformer_blocks.0.attn2.to_out.0": [7.832637786865234], "down_blocks.1.attentions.1.transformer_blocks.0.attn2.to_out.1": [5.94965934753418], "down_blocks.1.attentions.1.transformer_blocks.0.norm3": [21.295909881591797], "down_blocks.1.attentions.1.transformer_blocks.0.ff": [2.0267834663391113], "down_blocks.1.attentions.1.transformer_blocks.0.ff.net.0": [2.0267834663391113], "down_blocks.1.attentions.1.transformer_blocks.0.ff.net.0.proj": [2.0267834663391113], "down_blocks.1.attentions.1.transformer_blocks.0.ff.net.1": [93.98950958251953], "down_blocks.1.attentions.1.transformer_blocks.0.ff.net.2": [93.98950958251953], "down_blocks.1.attentions.1.proj_out": [30.745079040527344], "down_blocks.1.downsamplers.0": [243.6581268310547], "down_blocks.1.downsamplers.0.conv": [243.6581268310547], "down_blocks.2.resnets.0": [52.24580001831055, 5.55919885635376], "down_blocks.2.resnets.0.norm1": [52.24580001831055], "down_blocks.2.resnets.0.conv1": [10.94672679901123], "down_blocks.2.resnets.0.time_emb_proj": [5.537867546081543], "down_blocks.2.resnets.0.norm2": [61.874427795410156], "down_blocks.2.resnets.0.dropout": [9.346571922302246], "down_blocks.2.resnets.0.conv2": [9.346571922302246], "down_blocks.2.resnets.0.conv_shortcut": [52.24580001831055], "down_blocks.2.attentions.0": [29.484561920166016], "down_blocks.2.attentions.0.norm": [29.484561920166016], "down_blocks.2.attentions.0.proj_in": [3.7343106269836426], "down_blocks.2.attentions.0.transformer_blocks.0": [23.793006896972656], "down_blocks.2.attentions.0.transformer_blocks.0.norm1": [23.793006896972656], "down_blocks.2.attentions.0.transformer_blocks.0.attn1": [3.249636173248291], "down_blocks.2.attentions.0.transformer_blocks.0.attn1.to_q": [3.249636173248291], "down_blocks.2.attentions.0.transformer_blocks.0.attn1.to_k": [3.249636173248291], "down_blocks.2.attentions.0.transformer_blocks.0.attn1.to_v": [3.249636173248291], "down_blocks.2.attentions.0.transformer_blocks.0.attn1.to_out.0": [2.512848138809204], "down_blocks.2.attentions.0.transformer_blocks.0.attn1.to_out.1": [12.406010627746582], "down_blocks.2.attentions.0.transformer_blocks.0.norm2": [17.02704429626465], "down_blocks.2.attentions.0.transformer_blocks.0.attn2": [2.4004368782043457], "down_blocks.2.attentions.0.transformer_blocks.0.attn2.to_q": [2.4004368782043457], "down_blocks.2.attentions.0.transformer_blocks.0.attn2.to_k": [13.78433895111084], "down_blocks.2.attentions.0.transformer_blocks.0.attn2.to_v": [13.78433895111084], "down_blocks.2.attentions.0.transformer_blocks.0.attn2.to_out.0": [5.236146450042725], "down_blocks.2.attentions.0.transformer_blocks.0.attn2.to_out.1": [3.729442596435547], "down_blocks.2.attentions.0.transformer_blocks.0.norm3": [17.48666763305664], "down_blocks.2.attentions.0.transformer_blocks.0.ff": [2.502833127975464], "down_blocks.2.attentions.0.transformer_blocks.0.ff.net.0": [2.502833127975464], "down_blocks.2.attentions.0.transformer_blocks.0.ff.net.0.proj": [2.502833127975464], "down_blocks.2.attentions.0.transformer_blocks.0.ff.net.1": [20.099414825439453], "down_blocks.2.attentions.0.transformer_blocks.0.ff.net.2": [20.099414825439453], "down_blocks.2.attentions.0.proj_out": [11.020769119262695], "down_blocks.2.resnets.1": [24.96244239807129, 5.55919885635376], "down_blocks.2.resnets.1.norm1": [24.96244239807129], "down_blocks.2.resnets.1.conv1": [7.006809711456299], "down_blocks.2.resnets.1.time_emb_proj": [5.537867546081543], "down_blocks.2.resnets.1.norm2": [49.570762634277344], "down_blocks.2.resnets.1.dropout": [10.055081367492676], "down_blocks.2.resnets.1.conv2": [10.055081367492676], "down_blocks.2.attentions.1": [24.473094940185547], "down_blocks.2.attentions.1.norm": [24.473094940185547], "down_blocks.2.attentions.1.proj_in": [3.7222509384155273], "down_blocks.2.attentions.1.transformer_blocks.0": [20.396968841552734], "down_blocks.2.attentions.1.transformer_blocks.0.norm1": [20.396968841552734], "down_blocks.2.attentions.1.transformer_blocks.0.attn1": [2.4783694744110107], "down_blocks.2.attentions.1.transformer_blocks.0.attn1.to_q": [2.4783694744110107], "down_blocks.2.attentions.1.transformer_blocks.0.attn1.to_k": [2.4783694744110107], "down_blocks.2.attentions.1.transformer_blocks.0.attn1.to_v": [2.4783694744110107], "down_blocks.2.attentions.1.transformer_blocks.0.attn1.to_out.0": [2.9460201263427734], "down_blocks.2.attentions.1.transformer_blocks.0.attn1.to_out.1": [18.459331512451172], "down_blocks.2.attentions.1.transformer_blocks.0.norm2": [20.248292922973633], "down_blocks.2.attentions.1.transformer_blocks.0.attn2": [2.1530981063842773], "down_blocks.2.attentions.1.transformer_blocks.0.attn2.to_q": [2.1530981063842773], "down_blocks.2.attentions.1.transformer_blocks.0.attn2.to_k": [13.78433895111084], "down_blocks.2.attentions.1.transformer_blocks.0.attn2.to_v": [13.78433895111084], "down_blocks.2.attentions.1.transformer_blocks.0.attn2.to_out.0": [5.9958086013793945], "down_blocks.2.attentions.1.transformer_blocks.0.attn2.to_out.1": [3.1278281211853027], "down_blocks.2.attentions.1.transformer_blocks.0.norm3": [19.471010208129883], "down_blocks.2.attentions.1.transformer_blocks.0.ff": [2.167743444442749], "down_blocks.2.attentions.1.transformer_blocks.0.ff.net.0": [2.167743444442749], "down_blocks.2.attentions.1.transformer_blocks.0.ff.net.0.proj": [2.167743444442749], "down_blocks.2.attentions.1.transformer_blocks.0.ff.net.1": [17.057281494140625], "down_blocks.2.attentions.1.transformer_blocks.0.ff.net.2": [17.057281494140625], "down_blocks.2.attentions.1.proj_out": [12.909439086914062], "down_blocks.2.downsamplers.0": [34.30320358276367], "down_blocks.2.downsamplers.0.conv": [34.30320358276367], "down_blocks.3.resnets.0": [70.68637084960938, 5.55919885635376], "down_blocks.3.resnets.0.norm1": [70.68637084960938], "down_blocks.3.resnets.0.conv1": [6.269649505615234], "down_blocks.3.resnets.0.time_emb_proj": [5.537867546081543], "down_blocks.3.resnets.0.norm2": [12.532112121582031], "down_blocks.3.resnets.0.dropout": [10.398078918457031], "down_blocks.3.resnets.0.conv2": [10.398078918457031], "down_blocks.3.resnets.1": [61.06251525878906, 5.55919885635376], "down_blocks.3.resnets.1.norm1": [61.06251525878906], "down_blocks.3.resnets.1.conv1": [4.713294506072998], "down_blocks.3.resnets.1.time_emb_proj": [5.537867546081543], "down_blocks.3.resnets.1.norm2": [6.601444721221924], "down_blocks.3.resnets.1.dropout": [8.414468765258789], "down_blocks.3.resnets.1.conv2": [8.414468765258789], "mid_block": [63.69267272949219, 5.55919885635376], "mid_block.resnets.0": [63.69267272949219, 5.55919885635376], "mid_block.resnets.0.norm1": [63.69267272949219], "mid_block.resnets.0.conv1": [5.9842000007629395], "mid_block.resnets.0.time_emb_proj": [5.537867546081543], "mid_block.resnets.0.norm2": [7.460168838500977], "mid_block.resnets.0.dropout": [11.44105052947998], "mid_block.resnets.0.conv2": [11.44105052947998], "mid_block.attentions.0": [59.421104431152344], "mid_block.attentions.0.norm": [59.421104431152344], "mid_block.attentions.0.proj_in": [3.5983951091766357], "mid_block.attentions.0.transformer_blocks.0": [8.773942947387695], "mid_block.attentions.0.transformer_blocks.0.norm1": [8.773942947387695], "mid_block.attentions.0.transformer_blocks.0.attn1": [1.9067988395690918], "mid_block.attentions.0.transformer_blocks.0.attn1.to_q": [1.9067988395690918], "mid_block.attentions.0.transformer_blocks.0.attn1.to_k": [1.9067988395690918], "mid_block.attentions.0.transformer_blocks.0.attn1.to_v": [1.9067988395690918], "mid_block.attentions.0.transformer_blocks.0.attn1.to_out.0": [2.4993793964385986], "mid_block.attentions.0.transformer_blocks.0.attn1.to_out.1": [3.7747416496276855], "mid_block.attentions.0.transformer_blocks.0.norm2": [8.304662704467773], "mid_block.attentions.0.transformer_blocks.0.attn2": [2.694305896759033], "mid_block.attentions.0.transformer_blocks.0.attn2.to_q": [2.694305896759033], "mid_block.attentions.0.transformer_blocks.0.attn2.to_k": [13.78433895111084], "mid_block.attentions.0.transformer_blocks.0.attn2.to_v": [13.78433895111084], "mid_block.attentions.0.transformer_blocks.0.attn2.to_out.0": [4.162325859069824], "mid_block.attentions.0.transformer_blocks.0.attn2.to_out.1": [3.668454170227051], "mid_block.attentions.0.transformer_blocks.0.norm3": [10.945730209350586], "mid_block.attentions.0.transformer_blocks.0.ff": [2.528564691543579], "mid_block.attentions.0.transformer_blocks.0.ff.net.0": [2.528564691543579], "mid_block.attentions.0.transformer_blocks.0.ff.net.0.proj": [2.528564691543579], "mid_block.attentions.0.transformer_blocks.0.ff.net.1": [20.767200469970703], "mid_block.attentions.0.transformer_blocks.0.ff.net.2": [20.767200469970703], "mid_block.attentions.0.proj_out": [9.806567192077637], "mid_block.resnets.1": [64.5282211303711, 5.55919885635376], "mid_block.resnets.1.norm1": [64.5282211303711], "mid_block.resnets.1.conv1": [5.419158935546875], "mid_block.resnets.1.time_emb_proj": [5.537867546081543], "mid_block.resnets.1.norm2": [8.609598159790039], "mid_block.resnets.1.dropout": [10.487065315246582], "mid_block.resnets.1.conv2": [10.487065315246582], "up_blocks.0.resnets.0": [67.1644058227539, 5.55919885635376], "up_blocks.0.resnets.0.norm1": [67.1644058227539], "up_blocks.0.resnets.0.conv1": [4.41369104385376], "up_blocks.0.resnets.0.time_emb_proj": [5.537867546081543], "up_blocks.0.resnets.0.norm2": [13.862052917480469], "up_blocks.0.resnets.0.dropout": [16.070165634155273], "up_blocks.0.resnets.0.conv2": [16.070165634155273], "up_blocks.0.resnets.0.conv_shortcut": [67.1644058227539], "up_blocks.0.resnets.1": [67.74369812011719, 5.55919885635376], "up_blocks.0.resnets.1.norm1": [67.74369812011719], "up_blocks.0.resnets.1.conv1": [9.165180206298828], "up_blocks.0.resnets.1.time_emb_proj": [5.537867546081543], "up_blocks.0.resnets.1.norm2": [13.763409614562988], "up_blocks.0.resnets.1.dropout": [9.892571449279785], "up_blocks.0.resnets.1.conv2": [9.892571449279785], "up_blocks.0.resnets.1.conv_shortcut": [67.74369812011719], "up_blocks.0.resnets.2": [70.68637084960938, 5.55919885635376], "up_blocks.0.resnets.2.norm1": [70.68637084960938], "up_blocks.0.resnets.2.conv1": [6.606893062591553], "up_blocks.0.resnets.2.time_emb_proj": [5.537867546081543], "up_blocks.0.resnets.2.norm2": [27.536479949951172], "up_blocks.0.resnets.2.dropout": [9.520865440368652], "up_blocks.0.resnets.2.conv2": [9.520865440368652], "up_blocks.0.resnets.2.conv_shortcut": [70.68637084960938], "up_blocks.0.upsamplers.0": [23.899433135986328, 0], "up_blocks.0.upsamplers.0.conv": [23.899433135986328], "up_blocks.1.resnets.0": [57.73706817626953, 5.55919885635376], "up_blocks.1.resnets.0.norm1": [57.73706817626953], "up_blocks.1.resnets.0.conv1": [10.38025951385498], "up_blocks.1.resnets.0.time_emb_proj": [5.537867546081543], "up_blocks.1.resnets.0.norm2": [63.47644805908203], "up_blocks.1.resnets.0.dropout": [10.376016616821289], "up_blocks.1.resnets.0.conv2": [10.376016616821289], "up_blocks.1.resnets.0.conv_shortcut": [57.73706817626953], "up_blocks.1.attentions.0": [37.537689208984375], "up_blocks.1.attentions.0.norm": [37.537689208984375], "up_blocks.1.attentions.0.proj_in": [5.157177448272705], "up_blocks.1.attentions.0.transformer_blocks.0": [27.037050247192383], "up_blocks.1.attentions.0.transformer_blocks.0.norm1": [27.037050247192383], "up_blocks.1.attentions.0.transformer_blocks.0.attn1": [3.23549747467041], "up_blocks.1.attentions.0.transformer_blocks.0.attn1.to_q": [3.23549747467041], "up_blocks.1.attentions.0.transformer_blocks.0.attn1.to_k": [3.23549747467041], "up_blocks.1.attentions.0.transformer_blocks.0.attn1.to_v": [3.23549747467041], "up_blocks.1.attentions.0.transformer_blocks.0.attn1.to_out.0": [4.681851387023926], "up_blocks.1.attentions.0.transformer_blocks.0.attn1.to_out.1": [18.069866180419922], "up_blocks.1.attentions.0.transformer_blocks.0.norm2": [28.957063674926758], "up_blocks.1.attentions.0.transformer_blocks.0.attn2": [3.4627270698547363], "up_blocks.1.attentions.0.transformer_blocks.0.attn2.to_q": [3.4627270698547363], "up_blocks.1.attentions.0.transformer_blocks.0.attn2.to_k": [13.78433895111084], "up_blocks.1.attentions.0.transformer_blocks.0.attn2.to_v": [13.78433895111084], "up_blocks.1.attentions.0.transformer_blocks.0.attn2.to_out.0": [5.418970108032227], "up_blocks.1.attentions.0.transformer_blocks.0.attn2.to_out.1": [9.49647045135498], "up_blocks.1.attentions.0.transformer_blocks.0.norm3": [31.752117156982422], "up_blocks.1.attentions.0.transformer_blocks.0.ff": [3.496398687362671], "up_blocks.1.attentions.0.transformer_blocks.0.ff.net.0": [3.496398687362671], "up_blocks.1.attentions.0.transformer_blocks.0.ff.net.0.proj": [3.496398687362671], "up_blocks.1.attentions.0.transformer_blocks.0.ff.net.1": [27.482664108276367], "up_blocks.1.attentions.0.transformer_blocks.0.ff.net.2": [27.482664108276367], "up_blocks.1.attentions.0.proj_out": [23.193742752075195], "up_blocks.1.resnets.1": [40.112060546875, 5.55919885635376], "up_blocks.1.resnets.1.norm1": [40.112060546875], "up_blocks.1.resnets.1.conv1": [8.651629447937012], "up_blocks.1.resnets.1.time_emb_proj": [5.537867546081543], "up_blocks.1.resnets.1.norm2": [36.0448112487793], "up_blocks.1.resnets.1.dropout": [10.423382759094238], "up_blocks.1.resnets.1.conv2": [10.423382759094238], "up_blocks.1.resnets.1.conv_shortcut": [40.112060546875], "up_blocks.1.attentions.1": [47.19645690917969], "up_blocks.1.attentions.1.norm": [47.19645690917969], "up_blocks.1.attentions.1.proj_in": [5.158578395843506], "up_blocks.1.attentions.1.transformer_blocks.0": [34.62522506713867], "up_blocks.1.attentions.1.transformer_blocks.0.norm1": [34.62522506713867], "up_blocks.1.attentions.1.transformer_blocks.0.attn1": [3.329322576522827], "up_blocks.1.attentions.1.transformer_blocks.0.attn1.to_q": [3.329322576522827], "up_blocks.1.attentions.1.transformer_blocks.0.attn1.to_k": [3.329322576522827], "up_blocks.1.attentions.1.transformer_blocks.0.attn1.to_v": [3.329322576522827], "up_blocks.1.attentions.1.transformer_blocks.0.attn1.to_out.0": [3.6312756538391113], "up_blocks.1.attentions.1.transformer_blocks.0.attn1.to_out.1": [27.390634536743164], "up_blocks.1.attentions.1.transformer_blocks.0.norm2": [38.696598052978516], "up_blocks.1.attentions.1.transformer_blocks.0.attn2": [3.6385788917541504], "up_blocks.1.attentions.1.transformer_blocks.0.attn2.to_q": [3.6385788917541504], "up_blocks.1.attentions.1.transformer_blocks.0.attn2.to_k": [13.78433895111084], "up_blocks.1.attentions.1.transformer_blocks.0.attn2.to_v": [13.78433895111084], "up_blocks.1.attentions.1.transformer_blocks.0.attn2.to_out.0": [5.492264270782471], "up_blocks.1.attentions.1.transformer_blocks.0.attn2.to_out.1": [5.355135917663574], "up_blocks.1.attentions.1.transformer_blocks.0.norm3": [41.627777099609375], "up_blocks.1.attentions.1.transformer_blocks.0.ff": [2.9203131198883057], "up_blocks.1.attentions.1.transformer_blocks.0.ff.net.0": [2.9203131198883057], "up_blocks.1.attentions.1.transformer_blocks.0.ff.net.0.proj": [2.9203131198883057], "up_blocks.1.attentions.1.transformer_blocks.0.ff.net.1": [65.84680938720703], "up_blocks.1.attentions.1.transformer_blocks.0.ff.net.2": [65.84680938720703], "up_blocks.1.attentions.1.proj_out": [29.425729751586914], "up_blocks.1.resnets.2": [56.99182891845703, 5.55919885635376], "up_blocks.1.resnets.2.norm1": [56.99182891845703], "up_blocks.1.resnets.2.conv1": [11.262567520141602], "up_blocks.1.resnets.2.time_emb_proj": [5.537867546081543], "up_blocks.1.resnets.2.norm2": [589.7357177734375], "up_blocks.1.resnets.2.dropout": [12.607922554016113], "up_blocks.1.resnets.2.conv2": [12.607922554016113], "up_blocks.1.resnets.2.conv_shortcut": [56.99182891845703], "up_blocks.1.attentions.2": [50.18838882446289], "up_blocks.1.attentions.2.norm": [50.18838882446289], "up_blocks.1.attentions.2.proj_in": [6.560780048370361], "up_blocks.1.attentions.2.transformer_blocks.0": [211.4151611328125], "up_blocks.1.attentions.2.transformer_blocks.0.norm1": [211.4151611328125], "up_blocks.1.attentions.2.transformer_blocks.0.attn1": [3.9467389583587646], "up_blocks.1.attentions.2.transformer_blocks.0.attn1.to_q": [3.9467389583587646], "up_blocks.1.attentions.2.transformer_blocks.0.attn1.to_k": [3.9467389583587646], "up_blocks.1.attentions.2.transformer_blocks.0.attn1.to_v": [3.9467389583587646], "up_blocks.1.attentions.2.transformer_blocks.0.attn1.to_out.0": [4.041245460510254], "up_blocks.1.attentions.2.transformer_blocks.0.attn1.to_out.1": [48.39960479736328], "up_blocks.1.attentions.2.transformer_blocks.0.norm2": [195.91685485839844], "up_blocks.1.attentions.2.transformer_blocks.0.attn2": [6.300063133239746], "up_blocks.1.attentions.2.transformer_blocks.0.attn2.to_q": [6.300063133239746], "up_blocks.1.attentions.2.transformer_blocks.0.attn2.to_k": [13.78433895111084], "up_blocks.1.attentions.2.transformer_blocks.0.attn2.to_v": [13.78433895111084], "up_blocks.1.attentions.2.transformer_blocks.0.attn2.to_out.0": [11.555769920349121], "up_blocks.1.attentions.2.transformer_blocks.0.attn2.to_out.1": [17.469709396362305], "up_blocks.1.attentions.2.transformer_blocks.0.norm3": [202.2261962890625], "up_blocks.1.attentions.2.transformer_blocks.0.ff": [3.5171029567718506], "up_blocks.1.attentions.2.transformer_blocks.0.ff.net.0": [3.5171029567718506], "up_blocks.1.attentions.2.transformer_blocks.0.ff.net.0.proj": [3.5171029567718506], "up_blocks.1.attentions.2.transformer_blocks.0.ff.net.1": [38.47382736206055], "up_blocks.1.attentions.2.transformer_blocks.0.ff.net.2": [38.47382736206055], "up_blocks.1.attentions.2.proj_out": [180.62831115722656], "up_blocks.1.upsamplers.0": [39.75408935546875, 0], "up_blocks.1.upsamplers.0.conv": [39.75408935546875], "up_blocks.2.resnets.0": [243.6581268310547, 5.55919885635376], "up_blocks.2.resnets.0.norm1": [243.6581268310547], "up_blocks.2.resnets.0.conv1": [24.598249435424805], "up_blocks.2.resnets.0.time_emb_proj": [5.537867546081543], "up_blocks.2.resnets.0.norm2": [226.58047485351562], "up_blocks.2.resnets.0.dropout": [61.30534362792969], "up_blocks.2.resnets.0.conv2": [61.30534362792969], "up_blocks.2.resnets.0.conv_shortcut": [243.6581268310547], "up_blocks.2.attentions.0": [159.37791442871094], "up_blocks.2.attentions.0.norm": [159.37791442871094], "up_blocks.2.attentions.0.proj_in": [29.330427169799805], "up_blocks.2.attentions.0.transformer_blocks.0": [391.63262939453125], "up_blocks.2.attentions.0.transformer_blocks.0.norm1": [391.63262939453125], "up_blocks.2.attentions.0.transformer_blocks.0.attn1": [4.27008056640625], "up_blocks.2.attentions.0.transformer_blocks.0.attn1.to_q": [4.27008056640625], "up_blocks.2.attentions.0.transformer_blocks.0.attn1.to_k": [4.27008056640625], "up_blocks.2.attentions.0.transformer_blocks.0.attn1.to_v": [4.27008056640625], "up_blocks.2.attentions.0.transformer_blocks.0.attn1.to_out.0": [7.5140910148620605], "up_blocks.2.attentions.0.transformer_blocks.0.attn1.to_out.1": [34.45986557006836], "up_blocks.2.attentions.0.transformer_blocks.0.norm2": [396.009033203125], "up_blocks.2.attentions.0.transformer_blocks.0.attn2": [5.416439533233643], "up_blocks.2.attentions.0.transformer_blocks.0.attn2.to_q": [5.416439533233643], "up_blocks.2.attentions.0.transformer_blocks.0.attn2.to_k": [13.78433895111084], "up_blocks.2.attentions.0.transformer_blocks.0.attn2.to_v": [13.78433895111084], "up_blocks.2.attentions.0.transformer_blocks.0.attn2.to_out.0": [7.651183128356934], "up_blocks.2.attentions.0.transformer_blocks.0.attn2.to_out.1": [10.065694808959961], "up_blocks.2.attentions.0.transformer_blocks.0.norm3": [401.0743713378906], "up_blocks.2.attentions.0.transformer_blocks.0.ff": [4.459329128265381], "up_blocks.2.attentions.0.transformer_blocks.0.ff.net.0": [4.459329128265381], "up_blocks.2.attentions.0.transformer_blocks.0.ff.net.0.proj": [4.459329128265381], "up_blocks.2.attentions.0.transformer_blocks.0.ff.net.1": [375.9877624511719], "up_blocks.2.attentions.0.transformer_blocks.0.ff.net.2": [375.9877624511719], "up_blocks.2.attentions.0.proj_out": [397.64031982421875], "up_blocks.2.resnets.1": [649.9360961914062, 5.55919885635376], "up_blocks.2.resnets.1.norm1": [649.9360961914062], "up_blocks.2.resnets.1.conv1": [16.42521858215332], "up_blocks.2.resnets.1.time_emb_proj": [5.537867546081543], "up_blocks.2.resnets.1.norm2": [66.25425720214844], "up_blocks.2.resnets.1.dropout": [31.221113204956055], "up_blocks.2.resnets.1.conv2": [31.221113204956055], "up_blocks.2.resnets.1.conv_shortcut": [649.9360961914062], "up_blocks.2.attentions.1": [207.4163360595703], "up_blocks.2.attentions.1.norm": [207.4163360595703], "up_blocks.2.attentions.1.proj_in": [42.36643981933594], "up_blocks.2.attentions.1.transformer_blocks.0": [255.40338134765625], "up_blocks.2.attentions.1.transformer_blocks.0.norm1": [255.40338134765625], "up_blocks.2.attentions.1.transformer_blocks.0.attn1": [4.2503485679626465], "up_blocks.2.attentions.1.transformer_blocks.0.attn1.to_q": [4.2503485679626465], "up_blocks.2.attentions.1.transformer_blocks.0.attn1.to_k": [4.2503485679626465], "up_blocks.2.attentions.1.transformer_blocks.0.attn1.to_v": [4.2503485679626465], "up_blocks.2.attentions.1.transformer_blocks.0.attn1.to_out.0": [5.443492412567139], "up_blocks.2.attentions.1.transformer_blocks.0.attn1.to_out.1": [15.756156921386719], "up_blocks.2.attentions.1.transformer_blocks.0.norm2": [255.7368621826172], "up_blocks.2.attentions.1.transformer_blocks.0.attn2": [5.4502034187316895], "up_blocks.2.attentions.1.transformer_blocks.0.attn2.to_q": [5.4502034187316895], "up_blocks.2.attentions.1.transformer_blocks.0.attn2.to_k": [13.78433895111084], "up_blocks.2.attentions.1.transformer_blocks.0.attn2.to_v": [13.78433895111084], "up_blocks.2.attentions.1.transformer_blocks.0.attn2.to_out.0": [4.526592254638672], "up_blocks.2.attentions.1.transformer_blocks.0.attn2.to_out.1": [3.1783828735351562], "up_blocks.2.attentions.1.transformer_blocks.0.norm3": [255.78831481933594], "up_blocks.2.attentions.1.transformer_blocks.0.ff": [4.88238000869751], "up_blocks.2.attentions.1.transformer_blocks.0.ff.net.0": [4.88238000869751], "up_blocks.2.attentions.1.transformer_blocks.0.ff.net.0.proj": [4.88238000869751], "up_blocks.2.attentions.1.transformer_blocks.0.ff.net.1": [20.864498138427734], "up_blocks.2.attentions.1.transformer_blocks.0.ff.net.2": [20.864498138427734], "up_blocks.2.attentions.1.proj_out": [260.3758544921875], "up_blocks.2.resnets.2": [301.77850341796875, 5.55919885635376], "up_blocks.2.resnets.2.norm1": [301.77850341796875], "up_blocks.2.resnets.2.conv1": [14.679020881652832], "up_blocks.2.resnets.2.time_emb_proj": [5.537867546081543], "up_blocks.2.resnets.2.norm2": [38.2406005859375], "up_blocks.2.resnets.2.dropout": [7.822765350341797], "up_blocks.2.resnets.2.conv2": [7.822765350341797], "up_blocks.2.resnets.2.conv_shortcut": [301.77850341796875], "up_blocks.2.attentions.2": [102.2603988647461], "up_blocks.2.attentions.2.norm": [102.2603988647461], "up_blocks.2.attentions.2.proj_in": [32.00724792480469], "up_blocks.2.attentions.2.transformer_blocks.0": [128.34921264648438], "up_blocks.2.attentions.2.transformer_blocks.0.norm1": [128.34921264648438], "up_blocks.2.attentions.2.transformer_blocks.0.attn1": [3.9572865962982178], "up_blocks.2.attentions.2.transformer_blocks.0.attn1.to_q": [3.9572865962982178], "up_blocks.2.attentions.2.transformer_blocks.0.attn1.to_k": [3.9572865962982178], "up_blocks.2.attentions.2.transformer_blocks.0.attn1.to_v": [3.9572865962982178], "up_blocks.2.attentions.2.transformer_blocks.0.attn1.to_out.0": [4.597455024719238], "up_blocks.2.attentions.2.transformer_blocks.0.attn1.to_out.1": [12.164033889770508], "up_blocks.2.attentions.2.transformer_blocks.0.norm2": [129.01290893554688], "up_blocks.2.attentions.2.transformer_blocks.0.attn2": [4.762662410736084], "up_blocks.2.attentions.2.transformer_blocks.0.attn2.to_q": [4.762662410736084], "up_blocks.2.attentions.2.transformer_blocks.0.attn2.to_k": [13.78433895111084], "up_blocks.2.attentions.2.transformer_blocks.0.attn2.to_v": [13.78433895111084], "up_blocks.2.attentions.2.transformer_blocks.0.attn2.to_out.0": [5.475295066833496], "up_blocks.2.attentions.2.transformer_blocks.0.attn2.to_out.1": [5.531859397888184], "up_blocks.2.attentions.2.transformer_blocks.0.norm3": [124.48482513427734], "up_blocks.2.attentions.2.transformer_blocks.0.ff": [3.600153684616089], "up_blocks.2.attentions.2.transformer_blocks.0.ff.net.0": [3.600153684616089], "up_blocks.2.attentions.2.transformer_blocks.0.ff.net.0.proj": [3.600153684616089], "up_blocks.2.attentions.2.transformer_blocks.0.ff.net.1": [14.608333587646484], "up_blocks.2.attentions.2.transformer_blocks.0.ff.net.2": [14.608333587646484], "up_blocks.2.attentions.2.proj_out": [129.1501007080078], "up_blocks.2.upsamplers.0": [57.25132751464844, 0], "up_blocks.2.upsamplers.0.conv": [57.25132751464844], "up_blocks.3.resnets.0": [312.04010009765625, 5.55919885635376], "up_blocks.3.resnets.0.norm1": [312.04010009765625], "up_blocks.3.resnets.0.conv1": [26.880271911621094], "up_blocks.3.resnets.0.time_emb_proj": [5.537867546081543], "up_blocks.3.resnets.0.norm2": [84.7243423461914], "up_blocks.3.resnets.0.dropout": [9.111907958984375], "up_blocks.3.resnets.0.conv2": [9.111907958984375], "up_blocks.3.resnets.0.conv_shortcut": [312.04010009765625], "up_blocks.3.attentions.0": [29.59419059753418], "up_blocks.3.attentions.0.norm": [29.59419059753418], "up_blocks.3.attentions.0.proj_in": [5.4823479652404785], "up_blocks.3.attentions.0.transformer_blocks.0": [7.5209503173828125], "up_blocks.3.attentions.0.transformer_blocks.0.norm1": [7.5209503173828125], "up_blocks.3.attentions.0.transformer_blocks.0.attn1": [4.28728723526001], "up_blocks.3.attentions.0.transformer_blocks.0.attn1.to_q": [4.28728723526001], "up_blocks.3.attentions.0.transformer_blocks.0.attn1.to_k": [4.28728723526001], "up_blocks.3.attentions.0.transformer_blocks.0.attn1.to_v": [4.28728723526001], "up_blocks.3.attentions.0.transformer_blocks.0.attn1.to_out.0": [3.3580358028411865], "up_blocks.3.attentions.0.transformer_blocks.0.attn1.to_out.1": [5.828235626220703], "up_blocks.3.attentions.0.transformer_blocks.0.norm2": [7.0600972175598145], "up_blocks.3.attentions.0.transformer_blocks.0.attn2": [3.9522221088409424], "up_blocks.3.attentions.0.transformer_blocks.0.attn2.to_q": [3.9522221088409424], "up_blocks.3.attentions.0.transformer_blocks.0.attn2.to_k": [13.78433895111084], "up_blocks.3.attentions.0.transformer_blocks.0.attn2.to_v": [13.78433895111084], "up_blocks.3.attentions.0.transformer_blocks.0.attn2.to_out.0": [6.575131893157959], "up_blocks.3.attentions.0.transformer_blocks.0.attn2.to_out.1": [2.6216559410095215], "up_blocks.3.attentions.0.transformer_blocks.0.norm3": [9.208715438842773], "up_blocks.3.attentions.0.transformer_blocks.0.ff": [4.188446521759033], "up_blocks.3.attentions.0.transformer_blocks.0.ff.net.0": [4.188446521759033], "up_blocks.3.attentions.0.transformer_blocks.0.ff.net.0.proj": [4.188446521759033], "up_blocks.3.attentions.0.transformer_blocks.0.ff.net.1": [60.39920425415039], "up_blocks.3.attentions.0.transformer_blocks.0.ff.net.2": [60.39920425415039], "up_blocks.3.attentions.0.proj_out": [15.068622589111328], "up_blocks.3.resnets.1": [29.983427047729492, 5.55919885635376], "up_blocks.3.resnets.1.norm1": [29.983427047729492], "up_blocks.3.resnets.1.conv1": [3.233272075653076], "up_blocks.3.resnets.1.time_emb_proj": [5.537867546081543], "up_blocks.3.resnets.1.norm2": [6.539215087890625], "up_blocks.3.resnets.1.dropout": [4.224375247955322], "up_blocks.3.resnets.1.conv2": [4.224375247955322], "up_blocks.3.resnets.1.conv_shortcut": [29.983427047729492], "up_blocks.3.attentions.1": [20.28128433227539], "up_blocks.3.attentions.1.norm": [20.28128433227539], "up_blocks.3.attentions.1.proj_in": [8.727095603942871], "up_blocks.3.attentions.1.transformer_blocks.0": [42.17729949951172], "up_blocks.3.attentions.1.transformer_blocks.0.norm1": [42.17729949951172], "up_blocks.3.attentions.1.transformer_blocks.0.attn1": [11.767871856689453], "up_blocks.3.attentions.1.transformer_blocks.0.attn1.to_q": [11.767871856689453], "up_blocks.3.attentions.1.transformer_blocks.0.attn1.to_k": [11.767871856689453], "up_blocks.3.attentions.1.transformer_blocks.0.attn1.to_v": [11.767871856689453], "up_blocks.3.attentions.1.transformer_blocks.0.attn1.to_out.0": [3.34991192817688], "up_blocks.3.attentions.1.transformer_blocks.0.attn1.to_out.1": [6.976609706878662], "up_blocks.3.attentions.1.transformer_blocks.0.norm2": [37.503089904785156], "up_blocks.3.attentions.1.transformer_blocks.0.attn2": [4.79534387588501], "up_blocks.3.attentions.1.transformer_blocks.0.attn2.to_q": [4.79534387588501], "up_blocks.3.attentions.1.transformer_blocks.0.attn2.to_k": [13.78433895111084], "up_blocks.3.attentions.1.transformer_blocks.0.attn2.to_v": [13.78433895111084], "up_blocks.3.attentions.1.transformer_blocks.0.attn2.to_out.0": [8.651297569274902], "up_blocks.3.attentions.1.transformer_blocks.0.attn2.to_out.1": [8.36626148223877], "up_blocks.3.attentions.1.transformer_blocks.0.norm3": [29.884328842163086], "up_blocks.3.attentions.1.transformer_blocks.0.ff": [3.714874029159546], "up_blocks.3.attentions.1.transformer_blocks.0.ff.net.0": [3.714874029159546], "up_blocks.3.attentions.1.transformer_blocks.0.ff.net.0.proj": [3.714874029159546], "up_blocks.3.attentions.1.transformer_blocks.0.ff.net.1": [21.944141387939453], "up_blocks.3.attentions.1.transformer_blocks.0.ff.net.2": [21.944141387939453], "up_blocks.3.attentions.1.proj_out": [29.997900009155273], "up_blocks.3.resnets.2": [29.26504898071289, 5.55919885635376], "up_blocks.3.resnets.2.norm1": [29.26504898071289], "up_blocks.3.resnets.2.conv1": [3.7314629554748535], "up_blocks.3.resnets.2.time_emb_proj": [5.537867546081543], "up_blocks.3.resnets.2.norm2": [12.764349937438965], "up_blocks.3.resnets.2.dropout": [9.806478500366211], "up_blocks.3.resnets.2.conv2": [9.806478500366211], "up_blocks.3.resnets.2.conv_shortcut": [29.26504898071289], "up_blocks.3.attentions.2": [54.994728088378906], "up_blocks.3.attentions.2.norm": [54.994728088378906], "up_blocks.3.attentions.2.proj_in": [3.503772735595703], "up_blocks.3.attentions.2.transformer_blocks.0": [19.509063720703125], "up_blocks.3.attentions.2.transformer_blocks.0.norm1": [19.509063720703125], "up_blocks.3.attentions.2.transformer_blocks.0.attn1": [21.21921730041504], "up_blocks.3.attentions.2.transformer_blocks.0.attn1.to_q": [21.21921730041504], "up_blocks.3.attentions.2.transformer_blocks.0.attn1.to_k": [21.21921730041504], "up_blocks.3.attentions.2.transformer_blocks.0.attn1.to_v": [21.21921730041504], "up_blocks.3.attentions.2.transformer_blocks.0.attn1.to_out.0": [2.8697621822357178], "up_blocks.3.attentions.2.transformer_blocks.0.attn1.to_out.1": [13.725944519042969], "up_blocks.3.attentions.2.transformer_blocks.0.norm2": [9.105340003967285], "up_blocks.3.attentions.2.transformer_blocks.0.attn2": [2.8956618309020996], "up_blocks.3.attentions.2.transformer_blocks.0.attn2.to_q": [2.8956618309020996], "up_blocks.3.attentions.2.transformer_blocks.0.attn2.to_k": [13.78433895111084], "up_blocks.3.attentions.2.transformer_blocks.0.attn2.to_v": [13.78433895111084], "up_blocks.3.attentions.2.transformer_blocks.0.attn2.to_out.0": [9.423554420471191], "up_blocks.3.attentions.2.transformer_blocks.0.attn2.to_out.1": [4.896535396575928], "up_blocks.3.attentions.2.transformer_blocks.0.norm3": [5.227712631225586], "up_blocks.3.attentions.2.transformer_blocks.0.ff": [2.951200008392334], "up_blocks.3.attentions.2.transformer_blocks.0.ff.net.0": [2.951200008392334], "up_blocks.3.attentions.2.transformer_blocks.0.ff.net.0.proj": [2.951200008392334], "up_blocks.3.attentions.2.transformer_blocks.0.ff.net.1": [15.684059143066406], "up_blocks.3.attentions.2.transformer_blocks.0.ff.net.2": [15.684059143066406], "up_blocks.3.attentions.2.proj_out": [8.898432731628418], "conv_norm_out": [89.88381958007812], "conv_out": [5.574729919433594]}